Metadata-Version: 1.0
Name: lloc
Version: 1.0
Summary: Work with stroke.
Home-page: UNKNOWN
Author: UNKNOWN
Author-email: mironrobloksi@gmail.com
License: UNKNOWN
Platform: UNKNOWN
